<?xml version="1.0" encoding="utf-8"?>
<!DOCTYPE hibernate-mapping PUBLIC "-//Hibernate/Hibernate Mapping DTD 3.0//EN"
"http://www.hibernate.org/dtd/hibernate-mapping-3.0.dtd">
<!-- 
    Mapping file autogenerated by MyEclipse Persistence Tools
-->
<hibernate-mapping>
    <class name="com.entity.Detail" table="detail" catalog="shopping">
        <id name="id" type="java.lang.Integer">
            <column name="id" />
            <generator class="identity" />
        </id>
        <many-to-one name="orders" class="com.entity.Orders" fetch="select">
            <column name="o_no" />
        </many-to-one>
        <property name="IId" type="java.lang.Integer">
            <column name="i_id" not-null="true" />
        </property>
        <property name="itemName" type="java.lang.String">
            <column name="itemName" length="100" not-null="true" />
        </property>
        <property name="itemCount" type="java.lang.Integer">
            <column name="itemCount" />
        </property>
        <property name="price" type="java.lang.Float">
            <column name="price" precision="12" scale="0" not-null="true" />
        </property>
    </class>
</hibernate-mapping>
